{"id": 175, "name": "Togepi", "types": ["Fairy"], "abilities": [{"name": "Hustle", "is_hidden": false}, {"name": "Serene Grace", "is_hidden": false}, {"name": "Super Luck", "is_hidden": true}], "color": "white", "evolution_line": {"id": 175, "evolves_to": [{"id": 176, "evolves_to": [{"id": 468}]}]}, "has_branched_evolution": false, "original_region": "Johto", "generation": "Generation II", "base_stats": {"HP": 35, "Attack": 20, "Defense": 65, "Special Attack": 40, "Special Defense": 65, "Speed": 20}}